{
  "schema": "tinkerden_command_packet_v0",
  "packet_id": "td_command_20260628043926_ceebd7",
  "title": "TinkerDen command surface command",
  "created_at": "2026-06-28T04:39:26.908Z",
  "from": "NerdkleOrganismProof@Betsy",
  "source": "NerdkleOrganismProof@Betsy",
  "target": "Dink@Betsy",
  "target_aeye": "Dink",
  "target_machine": "Betsy",
  "destination_id": "dink_betsy_aeye_inbox_v0",
  "destination_type": "aeye_inbox_v0",
  "internal_destination": "foreman/messages/inbox",
  "stream": "NERDKLE ORGANISM / ANSWER LOOP",
  "command": "REAL_RELAY_PROOF: Nerdkle organism worker must receive this packet, generate an answer, and return answer proof.",
  "status": "PACKET_WRITTEN",
  "packet_type": "REAL_RELAY_PROOF",
  "mission": "REAL_RELAY_PROOF: Nerdkle organism worker must receive this packet, generate an answer, and return answer proof.",
  "context": "Issued from Command Dash. Relay must write a linked Aeye inbox packet and return ACK / BLOCKER / ARTIFACT.",
  "do": [
    "Read this command packet.",
    "Write linked Aeye inbox custody files.",
    "Return a receipt linked to packet_id."
  ],
  "do_not": [
    "Do not call sender-side write proof.",
    "Do not use free-text routing.",
    "Do not auto-send outside the local filesystem relay."
  ],
  "output_required": "A linked receipt with packet hash and Aeye relay custody paths.",
  "receipt_required": "ACK",
  "required_return": "ACK / BLOCKER / ARTIFACT",
  "proof_rule": "Receiver must read the packet file and match the sender-side SHA-256 file hash before ACK.",
  "required_surfaces": {
    "inbox": "tinkerden/inbox",
    "receipts": "tinkerden/receipts",
    "recommendation_cards": "tinkerden/recommendations/recommendation_cards.json",
    "decision_ledger": "tinkerden/feedback/decision-ledger.jsonl"
  }
}
